{"cameraMode":{"drawMode":0,"name":"Shaded","section":"Shading Mode"},"sceneLighting":true,"audioPlay":false,"sceneViewState":{"m_AlwaysRefresh":false,"showFog":true,"showSkybox":true,"showFlares":true,"showImageEffects":true,"showParticleSystems":true,"showVisualEffectGraphs":true,"m_FxEnabled":true},"in2DMode":false,"pivot":{"x":0.0,"y":0.0,"z":0.0},"rotation":{"x":-0.007919185794889927,"y":0.9489981532096863,"z":-0.3142875134944916,"w":-0.023919086903333665},"size":2.3445522785186769,"orthographic":false}